crispy/__init__.py
crispy/grid_ridge.py
crispy/image_ridge_find.py
crispy/scms.py
crispy/visualize.py
crispy/pruning/Skeleton.py
crispy/pruning/__init__.py
crispy/pruning/_filfinder_length.py
crispy/pruning/pruning.py
crispy/pruning/structures.py
crispy_learn-1.3.1.dist-info/LICENSE
crispy_learn-1.3.1.dist-info/METADATA
crispy_learn-1.3.1.dist-info/WHEEL
crispy_learn-1.3.1.dist-info/top_level.txt
crispy_learn-1.3.1.dist-info/RECORD
