Metadata-Version: 2.2
Name: crispy-learn
Version: 1.3.1
Summary: Computational Ridge Identification with SCMS for Python
Home-page: https://github.com/mcyc/crispy
Author: Michael Chun-Yuan Chen
Author-email: Michael Chun-Yuan Chen <mcyc@users.noreply.github.com>
License:                     GNU GENERAL PUBLIC LICENSE
Project-URL: Source, https://github.com/mcyc/crispy
Classifier: Programming Language :: Python :: 3
Classifier: Programming Language :: Python :: 3.8
Classifier: Programming Language :: Python :: 3.9
Classifier: Programming Language :: Python :: 3.10
Classifier: Programming Language :: Python :: 3.11
Classifier: Programming Language :: Python :: 3.12
Classifier: License :: OSI Approved :: GNU Lesser General Public License v3 (LGPLv3)
Classifier: Operating System :: OS Independent
Classifier: Intended Audience :: Science/Research
Classifier: Topic :: Scientific/Engineering :: Astronomy
Requires-Python: >=3.8
License-File: LICENSE
Requires-Dist: numpy>=1.24
Requires-Dist: scipy
Requires-Dist: astropy
Requires-Dist: joblib
Requires-Dist: scikit-image>=0.16
Requires-Dist: scikit-learn
Requires-Dist: matplotlib
Requires-Dist: plotly
Provides-Extra: docs
Requires-Dist: sphinx>=7.3.7; extra == "docs"
Requires-Dist: sphinx-rtd-theme>=1.3; extra == "docs"
Requires-Dist: sphinx-autodoc-typehints>=2.3.0; extra == "docs"
Requires-Dist: nbsphinx>=0.9.6; extra == "docs"
Requires-Dist: sphinx-copybutton>=0.5.2; extra == "docs"
Requires-Dist: pydata-sphinx-theme>=0.15.3; extra == "docs"
Requires-Dist: numpydoc>=1.2.0; extra == "docs"
Requires-Dist: sphinx-issues>=2.0; extra == "docs"
Requires-Dist: sphinxext-opengraph>=0.9; extra == "docs"
Dynamic: author
Dynamic: home-page
Dynamic: requires-python
